lab5/part 5/cpu.v
`include "reg.v"
`include "alu.v"

    // opcodes
    // loadi= "00000000";
	// mov 	= "00000001";
	// add 	= "00000010";
	// sub 	= "00000011";
	// and 	= "00000100";
	// or 	= "00000101";
    // j	= "00000110";
	// beq	= "00000111";

module cpu (PC, INSTRUCTION, CLK, RESET );

    // port declaration
    input CLK, RESET;
    input [31:0] INSTRUCTION;
    output reg [31:0] PC ;
    
    // wires for internal implementation
    wire SUB_SELECT, IMM_SELECT, WRITE_ENABLE, ZERO,BRANCH,JUMP, AND_OUT, OR_OUT;
    wire [7:0] ALU_OUT, REGOUT1, REGOUT2, TWOS, SUB_RESULT, IMM_RESULT;
    wire [2:0] ALUOP;
    wire [31:0] NEXTPC,B_MUX_OUT, ADDR_OUT, NEXTPC2;
    
        //  opcode = INSTRUCTION[31:24]; // opcode
        //  rd = INSTRUCTION[23:16];     // destination
        //  rt = INSTRUCTION[15:8];      // operand 1
        //  rs = INSTRUCTION[7:0];       // operand 2 or immediate

    //  initiating the modules    
    cu mucu(ALUOP, WRITE_ENABLE,SUB_SELECT, IMM_SELECT ,BRANCH,JUMP, INSTRUCTION[31:24] );
    reg_file myregfile(ALU_OUT, REGOUT1, REGOUT2, INSTRUCTION[18:16], INSTRUCTION[10:8],INSTRUCTION[2:0], WRITE_ENABLE, CLK, RESET);
    twos_comp for_sub(TWOS, REGOUT2);
    mux select2s(SUB_RESULT, REGOUT2, TWOS, SUB_SELECT);
    mux immediate_or_reg(IMM_RESULT, SUB_RESULT, INSTRUCTION[7:0], IMM_SELECT);
    Alu alu(ZERO, ALU_OUT, REGOUT1, IMM_RESULT, ALUOP);  
    addr adr(NEXTPC, PC, 'd4);

    andgate a1(AND_OUT, BRANCH, ZERO);
    or or1(OR_OUT,AND_OUT,JUMP);
    newaddr na(ADDR_OUT, NEXTPC, INSTRUCTION[23:16]);
    //mux32 branch_mux(B_MUX_OUT, NEXTPC, ADDR_OUT , AND_OUT );
    mux32 jump_mux (NEXTPC2  ,NEXTPC, ADDR_OUT,JUMP);

    
    // pc update with clock
    always @(posedge CLK) begin
        if(RESET) PC = 0;
        else #1 PC = NEXTPC2;
    end

endmodule

// 2 into 1 mux
module mux (OUTPUT, INPUT1, INPUT2, SELECT);
    input SELECT;
    input[7:0] INPUT1, INPUT2;
    output reg [7:0] OUTPUT;
    always @(*) begin
        if (SELECT==0) OUTPUT = INPUT1;
        else if (SELECT == 1) OUTPUT = INPUT2;
        // else what should do
    end
    
endmodule

// 2s complement generator
module twos_comp (OUTPUT, INPUT);
    input[7:0] INPUT;
    output[7:0] OUTPUT;
    assign  #1 OUTPUT = ~INPUT+1;
       
endmodule

// control unit
module   cu(ALUOP, WRITEENABLE, MUXSUB, MUXIMM,BRANCH,JUMP, OPCODE);
    input [7:0] OPCODE;
    output reg WRITEENABLE, MUXSUB, MUXIMM, BRANCH, JUMP;
    output reg [2:0] ALUOP;

    always @(*) begin
        #1
        case (OPCODE)   /// INSTRUCTION[31:24]
            
            'b00000000: begin // loadi
                MUXIMM = 'b1 ;// select for immediate value for loadi 
                ALUOP = 3'b000;
                MUXSUB = 'b0;
                WRITEENABLE = 'b1;
                BRANCH = 'b0;
                JUMP = 'b0;

            end 

            'b00000001: begin  // mov
                MUXIMM = 'b0;
                ALUOP = 3'b000;
                MUXSUB = 'b0;
                WRITEENABLE = 'b1;
                BRANCH = 'b0;
                JUMP = 'b0;
            end

            'b00000010: begin // add
                MUXIMM = 'b0 ;
                ALUOP = 3'b001;
                MUXSUB = 'b0;
                WRITEENABLE = 'b1;
                BRANCH = 'b0;
                JUMP = 'b0;
            end
                
            'b00000011: begin // sub
                MUXIMM = 'b0 ;
                ALUOP = 3'b001;
                MUXSUB = 'b1;
                WRITEENABLE = 'b1;
                BRANCH = 'b0;
                JUMP = 'b0;
            end

            'b00000100: begin // and
                MUXIMM = 'b0 ;
                ALUOP = 3'b010;
                MUXSUB = 'b0;
                WRITEENABLE = 'b1;
                BRANCH = 'b0;
                JUMP = 'b0;
            end

            'b00000101: begin // or
                MUXIMM = 'b0 ;
                ALUOP = 3'b011;
                MUXSUB = 'b0;
                WRITEENABLE = 'b1;
                BRANCH = 'b0;
                JUMP = 'b0;
            end
            
            'b00000110: begin // jump
                MUXIMM = 'bx ;
                ALUOP = 3'bxxx;
                MUXSUB = 'bx;
                WRITEENABLE = 'b0;
                BRANCH = 'b0;
                JUMP = 'b1;
            end

            'b00000111: begin // branch
                MUXIMM = 'b0 ;
                ALUOP = 3'b000; // addd
                MUXSUB = 'b1;   // sub 
                WRITEENABLE = 'b0;
                BRANCH = 'b1;
                JUMP = 'b0;
            end

            default: begin
                MUXIMM = 'bx ;
                ALUOP = 3'bxxx;
                MUXSUB = 'bx;
                WRITEENABLE = 'b0;
                BRANCH = 'bx;
                JUMP = 'bx;
            end
                
        endcase   
    end
endmodule

// adder
module addr (NEXTPC, PC, FOUR);

input [31:0] PC, FOUR ;
output [31:0] NEXTPC;
assign  #1 NEXTPC =  PC + FOUR;


    
endmodule

// adder
module newaddr (NEW_ADDR, CURRENT_ADDR, OFFSET);

input[7:0] OFFSET;
input [31:0]  CURRENT_ADDR ;
output [31:0] NEW_ADDR;
wire[31:0] EXTENDED, SHIFTED;

assign EXTENDED = { {24{OFFSET[7]}}, OFFSET[7:0] };
assign SHIFTED = EXTENDED *4;
assign  #2 NEW_ADDR =  SHIFTED + CURRENT_ADDR ;


    
endmodule

// AND GATE
module andgate (OUTPUT, INPUT1, INPUT2);
    input INPUT1, INPUT2;
    output OUTPUT;
    assign OUTPUT = INPUT1 & INPUT2;
endmodule

// 32 bit 2 into 1 mux
module mux32 (OUTPUT, INPUT1, INPUT2, SELECT);
    input SELECT;
    input[31:0] INPUT1, INPUT2;
    output reg [31:0] OUTPUT;
    always @(*) begin
        if (SELECT==0) OUTPUT = INPUT1;
        else if (SELECT ==1) OUTPUT = INPUT2;
    end
    
endmodule

lab5/part 5/alu.v
module Alu (ZERO, RESULT, DATA1, DATA2, SELECT);

// port declaration
input [7:0] DATA1, DATA2;
input [2:0] SELECT;
output reg [7:0] RESULT;
output  ZERO;

wire [7:0] ADD_OUT, FORWARD_OUT, AND_OUT, OR_OUT;


// module initializw
Forward fwd1(FORWARD_OUT, DATA2 );
Add add1(ADD_OUT, DATA1, DATA2 );
And and1(AND_OUT, DATA1, DATA2 );
Or or1(OR_OUT, DATA1, DATA2 );


assign ZERO = ~(RESULT[0]|RESULT[1]|RESULT[2]|RESULT[3]|RESULT[4]|RESULT[5]|RESULT[6]|RESULT[7]);


always @(*) begin //always @(*) begin
    
    
    
      
    case (SELECT)
        'b000:
             RESULT = FORWARD_OUT;
        'b001:
            RESULT = ADD_OUT; 
        'b010:
            RESULT = AND_OUT; 
        'b011:
            RESULT = OR_OUT; 
        default:
            RESULT = 'b00000000;

    endcase

end

  


endmodule

// arithmatic modules

module Forward (FORWARD_OUT, DATA2);
    input [7:0]  DATA2;
    output [7:0] FORWARD_OUT;
    assign #1 FORWARD_OUT =  DATA2; 
    
endmodule

module Add (ADD_OUT, DATA1, DATA2);
    input [7:0] DATA1, DATA2;
    output [7:0] ADD_OUT;
    assign #2  ADD_OUT =  DATA1+DATA2; 
    
endmodule

module And (AND_OUT, DATA1, DATA2);
    input [7:0] DATA1, DATA2;
    output [7:0] AND_OUT;
    assign #1 AND_OUT =  DATA1 & DATA2; 
    
endmodule

module Or (OR_OUT, DATA1, DATA2);
    input [7:0] DATA1, DATA2;
    output [7:0] OR_OUT;
    assign  #1 OR_OUT =  DATA1 | DATA2; 
    
endmodule

lab5/reg.v
/*
 *
 *	Part 2 - Register File
 *  Group 2
 *
 */

module reg_file(IN, OUT1, OUT2, INADDRESS, OUT1ADDRESS, OUT2ADDRESS, WRITE, CLK, RESET);

	input WRITE, CLK, RESET;				// 1-bit inputs
	input [2:0] INADDRESS, OUT1ADDRESS, OUT2ADDRESS;	// 3-bits inputs
	input [7:0] IN;						// 8-bits input

	output [7:0] OUT1, OUT2;				// 8-bits outputs


	reg [7:0] registers[7:0];		// this represents the 8-bits(1 byte)  8 registers ( 8x8 registers )


	integer regNum ;			// represet the register number for the RESET task

	// assign given addresses values to OUT1 and OUT2 respectively. this is asynchronous therefore, we use blocking statement with delay 2 units
	assign #2 OUT1 = registers[OUT1ADDRESS];	
	assign #2 OUT2 = registers[OUT2ADDRESS];


	// write to given address register at positive edge of the clock
	always @(posedge CLK) 
	begin 
		// writting happens when WRITE is high. 
		// if statement includes only one row so don't use begin end keywords
		if ( WRITE )	
			
			// this is synchronous therefore, we use non-blocking statement with delay 1 unit.
			// write in to given register
			#1 registers[INADDRESS] <= IN ;


	

	// reset all the registers synchronously at the positive edge of the clock
	
	
		
		// reset all the registers when RESET is high. 
		if ( RESET ) #1
		begin
			/*
			for(regNum = 0; regNum < 8 ; regNum = regNum + 1)begin
			
				registers[regNum] <= 'b00000000;

			end
			*/
			registers[0] <= 'b00000000;
			registers[1] <= 'b00000000;
			registers[2] <= 'b00000000;
			registers[3] <= 'b00000000;
			registers[4] <= 'b00000000;
			registers[5] <= 'b00000000;
			registers[6] <= 'b00000000;
			registers[7] <= 'b00000000;
			
		end
	
	end

endmodule

lab5/cpu_tb.v
// Computer Architecture (CO224) - Lab 05
// Design: Testbench of Integrated CPU of Simple Processor
// Author: Isuru Nawinne

`include "cpu.v"

module cpu_tb;

    reg CLK, RESET;
    wire [31:0] PC ;
    wire [31:0] INSTRUCTION;
    
    /* 
    ------------------------
     SIMPLE INSTRUCTION MEM
    ------------------------
    */
    
    // TODO: Initialize an array of registers (8x1024) named 'instr_mem' to be used as instruction memory
	
	reg [7:0] instr_mem [1023:0]; 	// instruction array
    
    // TODO: Create combinational logic to support CPU instruction fetching, given the Program Counter(PC) value 
    //       (make sure you include the delay for instruction fetching here)
    
	assign #2 INSTRUCTION = {instr_mem[PC+3],instr_mem[PC+2],instr_mem[PC+1],instr_mem[PC]};	// fetching instruction with time delay
	
    initial
    begin
        // Initialize instruction memory with the set of instructions you need execute on CPU
        
        // METHOD 1: manually loading instructions to instr_mem
        //{instr_mem[10'd3], instr_mem[10'd2], instr_mem[10'd1], instr_mem[10'd0]} = 32'b00000000000001000000000000000101;
        //{instr_mem[10'd7], instr_mem[10'd6], instr_mem[10'd5], instr_mem[10'd4]} = 32'b00000000000000100000000000001001;
        //{instr_mem[10'd11], instr_mem[10'd10], instr_mem[10'd9], instr_mem[10'd8]} = 32'b00000010000001100000010000000010;
		
        // METHOD 2: loading instr_mem content from instr_mem.mem file
        $readmemb("instr_mem.mem", instr_mem);
    end
    
    /* 
    -----
     CPU
    -----
    */
    cpu mycpu(PC, INSTRUCTION, CLK, RESET);

    initial
    begin
    
        // generate files needed to plot the waveform using GTKWave
        $dumpfile("cpu_wavedata.vcd");
		$dumpvars(0, cpu_tb);
        
        CLK = 1'b0;
        RESET = 1'b0;
        
        // TODO: Reset the CPU (by giving a pulse to RESET signal) to start the program execution
        RESET = 1'b1;
        #5
        RESET = 1'b0;

        // reset check
        //#20
        //RESET = 1'b1;
        //#5
        //RESET = 1'b0;
        //
		
		
        // finish simulation after some time
        #500
        $finish;
        
    end
    
    // clock signal generation
    always
        #4 CLK = ~CLK;
        

endmodule

lab5/part 5/cpu_wavedata.vcd
$date
	Fri Feb  4 11:00:34 2022
$end
$version
	Icarus Verilog
$end
$timescale
	1s
$end
$scope module cpu_tb $end
$var wire 32 ! PC [31:0] $end
$var wire 32 " INSTRUCTION [31:0] $end
$var reg 1 # CLK $end
$var reg 1 $ RESET $end
$scope module mycpu $end
$var wire 1 # CLK $end
$var wire 32 % INSTRUCTION [31:0] $end
$var wire 1 & OR_OUT $end
$var wire 1 $ RESET $end
$var wire 1 ' ZERO $end
$var wire 1 ( WRITE_ENABLE $end
$var wire 8 ) TWOS [7:0] $end
$var wire 1 * SUB_SELECT $end
$var wire 8 + SUB_RESULT [7:0] $end
$var wire 8 , REGOUT2 [7:0] $end
$var wire 8 - REGOUT1 [7:0] $end
$var wire 32 . NEXTPC2 [31:0] $end
$var wire 32 / NEXTPC [31:0] $end
$var wire 1 0 JUMP $end
$var wire 1 1 IMM_SELECT $end
$var wire 8 2 IMM_RESULT [7:0] $end
$var wire 1 3 BRANCH $end
$var wire 1 4 AND_OUT $end
$var wire 8 5 ALU_OUT [7:0] $end
$var wire 3 6 ALUOP [2:0] $end
$var wire 32 7 ADDR_OUT [31:0] $end
$var reg 32 8 PC [31:0] $end
$scope module a1 $end
$var wire 1 4 OUTPUT $end
$var wire 1 ' INPUT2 $end
$var wire 1 3 INPUT1 $end
$upscope $end
$scope module adr $end
$var wire 32 9 FOUR [31:0] $end
$var wire 32 : PC [31:0] $end
$var wire 32 ; NEXTPC [31:0] $end
$upscope $end
$scope module alu $end
$var wire 1 ' ZERO $end
$var wire 3 < SELECT [2:0] $end
$var wire 8 = OR_OUT [7:0] $end
$var wire 8 > FORWARD_OUT [7:0] $end
$var wire 8 ? DATA2 [7:0] $end
$var wire 8 @ DATA1 [7:0] $end
$var wire 8 A AND_OUT [7:0] $end
$var wire 8 B ADD_OUT [7:0] $end
$var reg 8 C RESULT [7:0] $end
$scope module add1 $end
$var wire 8 D DATA2 [7:0] $end
$var wire 8 E DATA1 [7:0] $end
$var wire 8 F ADD_OUT [7:0] $end
$upscope $end
$scope module and1 $end
$var wire 8 G AND_OUT [7:0] $end
$var wire 8 H DATA2 [7:0] $end
$var wire 8 I DATA1 [7:0] $end
$upscope $end
$scope module fwd1 $end
$var wire 8 J FORWARD_OUT [7:0] $end
$var wire 8 K DATA2 [7:0] $end
$upscope $end
$scope module or1 $end
$var wire 8 L OR_OUT [7:0] $end
$var wire 8 M DATA2 [7:0] $end
$var wire 8 N DATA1 [7:0] $end
$upscope $end
$upscope $end
$scope module for_sub $end
$var wire 8 O OUTPUT [7:0] $end
$var wire 8 P INPUT [7:0] $end
$upscope $end
$scope module immediate_or_reg $end
$var wire 8 Q INPUT2 [7:0] $end
$var wire 1 1 SELECT $end
$var wire 8 R INPUT1 [7:0] $end
$var reg 8 S OUTPUT [7:0] $end
$upscope $end
$scope module jump_mux $end
$var wire 32 T INPUT1 [31:0] $end
$var wire 1 0 SELECT $end
$var wire 32 U INPUT2 [31:0] $end
$var reg 32 V OUTPUT [31:0] $end
$upscope $end
$scope module mucu $end
$var wire 8 W OPCODE [7:0] $end
$var reg 3 X ALUOP [2:0] $end
$var reg 1 3 BRANCH $end
$var reg 1 0 JUMP $end
$var reg 1 1 MUXIMM $end
$var reg 1 * MUXSUB $end
$var reg 1 ( WRITEENABLE $end
$upscope $end
$scope module myregfile $end
$var wire 1 # CLK $end
$var wire 8 Y IN [7:0] $end
$var wire 3 Z INADDRESS [2:0] $end
$var wire 8 [ OUT1 [7:0] $end
$var wire 3 \ OUT1ADDRESS [2:0] $end
$var wire 8 ] OUT2 [7:0] $end
$var wire 3 ^ OUT2ADDRESS [2:0] $end
$var wire 1 $ RESET $end
$var wire 1 ( WRITE $end
$upscope $end
$scope module na $end
$var wire 32 _ CURRENT_ADDR [31:0] $end
$var wire 8 ` OFFSET [7:0] $end
$var wire 32 a SHIFTED [31:0] $end
$var wire 32 b NEW_ADDR [31:0] $end
$var wire 32 c EXTENDED [31:0] $end
$upscope $end
$scope module select2s $end
$var wire 8 d INPUT1 [7:0] $end
$var wire 8 e INPUT2 [7:0] $end
$var wire 1 * SELECT $end
$var reg 8 f OUTPUT [7:0] $end
$upscope $end
$upscope $end
$upscope $end
$enddefinitions $end
#0
$dumpvars
bx f
bx e
bx d
bx c
bx b
bx a
bx `
bx _
bx ^
bx ]
bx \
bx [
bx Z
bx Y
bx X
bx W
bx V
bx U
bx T
bx S
bx R
bx Q
bx P
bx O
bx N
bx M
bx L
bx K
bx J
bx I
bx H
bx G
bx F
bx E
bx D
bx C
bx B
bx A
bx @
bx ?
bx >
bx =
bx <
bx ;
bx :
b100 9
bx 8
bx 7
bx 6
bx 5
x4
x3
bx 2
x1
x0
bx /
bx .
bx -
bx ,
bx +
x*
bx )
x(
x'
x&
bx %
1$
0#
bx "
bx !
$end
#4
b0 !
b0 8
b0 :
1#
#5
b100 /
b100 ;
b100 T
b100 _
0$
#6
b10000 a
b0 W
b100 Z
b0 \
b101 ^
b101 Q
b100 c
b100 `
b1000000000000000101 "
b1000000000000000101 %
#7
0&
b100 .
b100 V
04
b101 2
b101 ?
b101 D
b101 H
b101 K
b101 M
b101 S
00
03
1(
0*
b0 6
b0 <
b0 X
11
#8
0'
b101 5
b101 C
b101 Y
b0 +
b0 R
b0 f
bx1x1 =
bx1x1 L
b0x0x A
b0x0x G
b101 >
b101 J
b10100 7
b10100 U
b10100 b
b0 -
b0 @
b0 E
b0 I
b0 N
b0 [
b0 ,
b0 P
b0 ]
b0 d
0#
#9
b101 =
b101 L
b0 A
b0 G
b0 )
b0 O
b0 e
#10
b101 B
b101 F
#12
1#
#13
b100 !
b100 8
b100 :
#14
b1000 .
b1000 V
b1000 /
b1000 ;
b1000 T
b1000 _
#15
b101 Z
b10100 a
b101 c
b101 `
b1010000000000000101 "
b1010000000000000101 %
#16
0#
#17
b11100 7
b11100 U
b11100 b
#20
1#
#21
b1000 !
b1000 8
b1000 :
#22
b1100 .
b1100 V
b1100 /
b1100 ;
b1100 T
b1100 _
#23
b0 2
b0 ?
b0 D
b0 H
b0 K
b0 M
b0 S
b101 +
b101 R
b101 f
b110 W
b10 Z
b0 ^
b0 Q
b1000 a
b10 c
b10 `
b101 ,
b101 P
b101 ]
b101 d
b110000000100000000000000000 "
b110000000100000000000000000 %
#24
1'
1&
b11100 .
b11100 V
b0 5
b0 C
b0 Y
b0 =
b0 L
10
0(
x*
bx 6
bx <
bx X
x1
b0 >
b0 J
b11111011 )
b11111011 O
b11111011 e
0#
#25
b10100 .
b10100 V
b0 B
b0 F
b0 ,
b0 P
b0 ]
b0 d
b10100 7
b10100 U
b10100 b
#26
b0 )
b0 O
b0 e
#28
1#
#29
b10100 !
b10100 8
b10100 :
#30
b11000 /
b11000 ;
b11000 T
b11000 _
#31
b1 W
b0 Z
b110 ^
b110 Q
b0 a
b0 c
b0 `
b1000000000000000000000110 "
b1000000000000000000000110 %
#32
0&
b11000 .
b11000 V
b0 +
b0 R
b0 f
b0 2
b0 ?
b0 D
b0 H
b0 K
b0 M
b0 S
00
1(
0*
b0 6
b0 <
b0 X
01
0#
#33
b11000 7
b11000 U
b11000 b
#36
1#
#37
b11000 !
b11000 8
b11000 :
#38
b11100 .
b11100 V
b11100 /
b11100 ;
b11100 T
b11100 _
#39
b111 W
b110 Z
b100 \
b101 ^
b101 Q
b11111111111111111111111111111000 a
b11111111111111111111111111111110 c
b11111110 `
b111111111100000010000000101 "
b111111111100000010000000101 %
#40
1&
14
13
0(
1*
0#
#41
b101 -
b101 @
b101 E
b101 I
b101 N
b101 [
b101 ,
b101 P
b101 ]
b101 d
b10100 7
b10100 U
b10100 b
#42
b11111011 2
b11111011 ?
b11111011 D
b11111011 H
b11111011 K
b11111011 M
b11111011 S
b11111011 +
b11111011 R
b11111011 f
b101 =
b101 L
b11111011 )
b11111011 O
b11111011 e
#43
0&
04
0'
b11111011 5
b11111011 C
b11111011 Y
b11111111 =
b11111111 L
b1 A
b1 G
b11111011 >
b11111011 J
#44
1#
#45
b11100 !
b11100 8
b11100 :
#46
b100000 .
b100000 V
b100000 /
b100000 ;
b100000 T
b100000 _
#47
b0 W
b1 Z
b0 \
b1 ^
b1 Q
b100 a
b1 c
b1 `
b10000000000000001 "
b10000000000000001 %
#48
b101 +
b101 R
b101 f
b1 2
b1 ?
b1 D
b1 H
b1 K
b1 M
b1 S
03
1(
0*
11
0#
#49
b1 5
b1 C
b1 Y
b0 +
b0 R
b0 f
b101 =
b101 L
b1 >
b1 J
b0 -
b0 @
b0 E
b0 I
b0 N
b0 [
b0 ,
b0 P
b0 ]
b0 d
b100100 7
b100100 U
b100100 b
#50
b1 =
b1 L
b0 A
b0 G
b0 )
b0 O
b0 e
#51
b1 B
b1 F
#52
1#
#53
b100000 !
b100000 8
b100000 :
#54
b100100 .
b100100 V
b100100 /
b100100 ;
b100100 T
b100100 _
#55
b1 +
b1 R
b1 f
b10 W
b10 Z
b10 \
b1000 a
b10 c
b10 `
b1 ,
b1 P
b1 ]
b1 d
b10000000100000001000000001 "
b10000000100000001000000001 %
#56
b1 6
b1 <
b1 X
01
b11111111 )
b11111111 O
b11111111 e
0#
#57
b101100 7
b101100 U
b101100 b
#60
1#
#61
b100100 !
b100100 8
b100100 :
#62
b101000 .
b101000 V
b101000 /
b101000 ;
b101000 T
b101000 _
#63
bx W
bx Z
bx \
bx ^
bx Q
bx a
bx c
bx `
b1 -
b1 @
b1 E
b1 I
b1 N
b1 [
bx "
bx %
#64
x4
1'
x&
b0 5
b0 C
b0 Y
x0
x3
0(
x*
bx 6
bx <
bx X
x1
b1 A
b1 G
0#
#65
bx -
bx @
bx E
bx I
bx N
bx [
bx ,
bx P
bx ]
bx d
bx 7
bx U
bx b
b10 B
b10 F
#66
bx1 =
bx1 L
b0x A
b0x G
bx )
bx O
bx e
#67
bx B
bx F
#68
1#
#69
b101000 !
b101000 8
b101000 :
#70
b101100 /
b101100 ;
b101100 T
b101100 _
#72
0#
1$
#74
0$
