lab5/cpu.v
`include "reg.v"
`include "alu.v"

    // opcodes
    // loadi= "00000000";
	// mov 	= "00000001";
	// add 	= "00000010";
	// sub 	= "00000011";
	// and 	= "00000100";
	// or 	= "00000101";

module cpu (PC, INSTRUCTION, CLK, RESET );
    input CLK, RESET;
    input [31:0] INSTRUCTION;
    output reg [31:0] PC ;
    

    wire SUB_SELECT, IMM_SELECT, WRITE_ENABLE;
    wire [7:0] ALU_OUT, REGOUT1, REGOUT2, TWOS, SUB_RESULT, IMM_RESULT, WRITE_DATA;
    wire [2:0] ALUOP;
    wire [31:0] NEXTPC;
    
        //  opcode = INSTRUCTION[31:24]; // opcode
        //  rd = INSTRUCTION[23:16];     // destination
        //  rt = INSTRUCTION[15:8];      // operand 1
        //  rs = INSTRUCTION[7:0];       // operand 2 or immediate
    cu mucu(ALUOP, WRITE_ENABLE,SUB_SELECT, IMM_SELECT , INSTRUCTION[31:24] );
    reg_file myregfile(ALU_OUT, REGOUT1, REGOUT2, INSTRUCTION[18:16], INSTRUCTION[10:8],INSTRUCTION[2:0], WRITE_ENABLE, CLK, RESET);
    twos_comp for_sub(TWOS, REGOUT2);
    mux select2s(SUB_RESULT, REGOUT2, TWOS, SUB_SELECT);
    mux immediate_or_reg(IMM_RESULT, SUB_RESULT, INSTRUCTION[7:0], IMM_SELECT);
    Alu alu(ALU_OUT, REGOUT1, IMM_RESULT, ALUOP);
    // pc update with #1     
    addr adr(NEXTPC, PC, 'd4);

    //assign WRITE_DATA = ALU_OUT;

    always @(posedge CLK, posedge RESET) begin
        if(RESET) PC = 0;
        else #1 PC = NEXTPC;
    end
    


    
endmodule

module mux (OUTPUT, INPUT1, INPUT2, SELECT);
    input SELECT;
    input[7:0] INPUT1, INPUT2;
    output reg [7:0] OUTPUT;
    always @(*) begin
        if (SELECT==0) OUTPUT = INPUT1;
        else OUTPUT = INPUT2;
    end
    
endmodule


module twos_comp (OUTPUT, INPUT);
    input[7:0] INPUT;
    output[7:0] OUTPUT;
    assign  #1 OUTPUT = ~INPUT+1;
    
    
endmodule

module   cu(ALUOP, WRITEENABLE, MUXSUB, MUXIMM, OPCODE);
    input [7:0] OPCODE;
    output reg WRITEENABLE, MUXSUB, MUXIMM;
    output reg [2:0] ALUOP;

    always @(*) begin
        #1
        case (OPCODE)   /// INSTRUCTION[31:24]
            
            'b00000000: begin // loadi
                MUXIMM = 'b1 ;// select for immediate value for loadi 
                ALUOP = 3'b000;
                MUXSUB = 'b0;
                WRITEENABLE = 'b1;

            end 

            'b000000011: begin  // mov
                MUXIMM = 'b0;
                ALUOP = 3'b000;
                MUXSUB = 'b0;
                WRITEENABLE = 'b1;
            end

            'b00000010: begin // add
                MUXIMM = 'b0 ;
                ALUOP = 3'b001;
                MUXSUB = 'b0;
                WRITEENABLE = 'b1;
            end
                
            'b00000011: begin // sub
                MUXIMM = 'b0 ;
                ALUOP = 3'b001;
                MUXSUB = 'b1;
                WRITEENABLE = 'b1;
            end

            'b00000100: begin // and
                MUXIMM = 'b0 ;
                ALUOP = 3'b010;
                MUXSUB = 'b0;
                WRITEENABLE = 'b1;
            end

            'b00000101: begin // or
                MUXIMM = 'b0 ;
                ALUOP = 3'b011;
                MUXSUB = 'b0;
                WRITEENABLE = 'b1;
            end

            // default: begin
            //     MUXIMM = 'b0 ;
            //     ALUOP = 3'b100;
            //     MUXSUB = 'b0;
            //     WRITEENABLE = 'b0;
            // end
                
        endcase   
    end
endmodule


module addr (NEXTPC, PC, FOUR);

input [31:0] PC, FOUR ;
output [31:0] NEXTPC;
assign  #1 NEXTPC =  PC + FOUR;


    
endmodule

lab5/alu.v
module Alu (RESULT, DATA1, DATA2, SELECT);

// port declaration
input [7:0] DATA1, DATA2;
input [2:0] SELECT;
output reg [7:0] RESULT;
wire [7:0] ADD_OUT, FORWARD_OUT, AND_OUT, OR_OUT;


// module initializw
Forward fwd1(FORWARD_OUT, DATA2 );
Add add1(ADD_OUT, DATA1, DATA2 );
And and1(AND_OUT, DATA1, DATA2 );
Or or1(OR_OUT, DATA1, DATA2 );

always @(*) begin //always @(*) begin
    

    case (SELECT)
        'b000:
             RESULT = FORWARD_OUT;
        'b001:
            RESULT = ADD_OUT; 
        'b010:
            RESULT = AND_OUT; 
        'b011:
             RESULT = OR_OUT; 
        default:
            RESULT = 'b00000000;

    endcase
end

endmodule

// arithmatic modules

module Forward (FORWARD_OUT, DATA2);
    input [7:0]  DATA2;
    output [7:0] FORWARD_OUT;
    assign #1 FORWARD_OUT =  DATA2; 
    
endmodule

module Add (ADD_OUT, DATA1, DATA2);
    input [7:0] DATA1, DATA2;
    output [7:0] ADD_OUT;
    assign #2  ADD_OUT =  DATA1+DATA2; 
    
endmodule

module And (AND_OUT, DATA1, DATA2);
    input [7:0] DATA1, DATA2;
    output [7:0] AND_OUT;
    assign #1 AND_OUT =  DATA1 & DATA2; 
    
endmodule

module Or (OR_OUT, DATA1, DATA2);
    input [7:0] DATA1, DATA2;
    output [7:0] OR_OUT;
    assign  #1 OR_OUT =  DATA1 | DATA2; 
    
endmodule

lab5/reg.v
/*
 *
 *	Part 2 - Register File
 *  Group 2
 *
 */

module reg_file(IN, OUT1, OUT2, INADDRESS, OUT1ADDRESS, OUT2ADDRESS, WRITE, CLK, RESET);

	input WRITE, CLK, RESET;				// 1-bit inputs
	input [2:0] INADDRESS, OUT1ADDRESS, OUT2ADDRESS;	// 3-bits inputs
	input [7:0] IN;						// 8-bits input

	output [7:0] OUT1, OUT2;				// 8-bits outputs


	reg [7:0] registers[7:0];		// this represents the 8-bits(1 byte)  8 registers ( 8x8 registers )


	integer regNum ;			// represet the register number for the RESET task

	// assign given addresses values to OUT1 and OUT2 respectively. this is asynchronous therefore, we use blocking statement with delay 2 units
	assign #2 OUT1 = registers[OUT1ADDRESS];	
	assign #2 OUT2 = registers[OUT2ADDRESS];


	// write to given address register at positive edge of the clock
	always @(posedge CLK) 
	begin 
		// writting happens when WRITE is high. 
		// if statement includes only one row so don't use begin end keywords
		if ( WRITE )	
			
			// this is synchronous therefore, we use non-blocking statement with delay 1 unit.
			// write in to given register
			#1 registers[INADDRESS] <= IN ;


	

	// reset all the registers synchronously at the positive edge of the clock
	
	
		
		// reset all the registers when RESET is high. 
		if ( RESET ) #1
		begin
			/*
			for(regNum = 0; regNum < 8 ; regNum = regNum + 1)begin
			
				registers[regNum] <= 'b00000000;

			end
			*/
			registers[0] <= 'b00000000;
			registers[1] <= 'b00000000;
			registers[2] <= 'b00000000;
			registers[3] <= 'b00000000;
			registers[4] <= 'b00000000;
			registers[5] <= 'b00000000;
			registers[6] <= 'b00000000;
			registers[7] <= 'b00000000;
			
		end
	
	end

endmodule

lab5/cpu_tb.v
// Computer Architecture (CO224) - Lab 05
// Design: Testbench of Integrated CPU of Simple Processor
// Author: Isuru Nawinne

`include "cpu.v"

module cpu_tb;

    reg CLK, RESET;
    wire [31:0] PC ;
    wire [31:0] INSTRUCTION;
    
    /* 
    ------------------------
     SIMPLE INSTRUCTION MEM
    ------------------------
    */
    
    // TODO: Initialize an array of registers (8x1024) named 'instr_mem' to be used as instruction memory
	
	reg [7:0] instr_mem [1023:0]; 	// instruction array
    
    // TODO: Create combinational logic to support CPU instruction fetching, given the Program Counter(PC) value 
    //       (make sure you include the delay for instruction fetching here)
    
	assign #2 INSTRUCTION = {instr_mem[PC+3],instr_mem[PC+2],instr_mem[PC+1],instr_mem[PC]};	// fetching instruction with time delay
	
    initial
    begin
        // Initialize instruction memory with the set of instructions you need execute on CPU
        
        // METHOD 1: manually loading instructions to instr_mem
        //{instr_mem[10'd3], instr_mem[10'd2], instr_mem[10'd1], instr_mem[10'd0]} = 32'b00000000000001000000000000000101;
        //{instr_mem[10'd7], instr_mem[10'd6], instr_mem[10'd5], instr_mem[10'd4]} = 32'b00000000000000100000000000001001;
        //{instr_mem[10'd11], instr_mem[10'd10], instr_mem[10'd9], instr_mem[10'd8]} = 32'b00000010000001100000010000000010;
		
        // METHOD 2: loading instr_mem content from instr_mem.mem file
        $readmemb("instr_mem.mem", instr_mem);
    end
    
    /* 
    -----
     CPU
    -----
    */
    cpu mycpu(PC, INSTRUCTION, CLK, RESET);

    initial
    begin
    
        // generate files needed to plot the waveform using GTKWave
        $dumpfile("cpu_wavedata.vcd");
		$dumpvars(0, cpu_tb);
        
        CLK = 1'b0;
        RESET = 1'b0;
        
        // TODO: Reset the CPU (by giving a pulse to RESET signal) to start the program execution
        RESET = 1'b1;
        #5
        RESET = 1'b0;

        // reset check
        //#20
        //RESET = 1'b1;
        //#5
        //RESET = 1'b0;
        //
		
		
        // finish simulation after some time
        #500
        $finish;
        
    end
    
    // clock signal generation
    always
        #4 CLK = ~CLK;
        

endmodule

lab5/cpu_wavedata.vcd
$date
	Sun Jan 23 08:17:39 2022
$end
$version
	Icarus Verilog
$end
$timescale
	1s
$end
$scope module cpu_tb $end
$var wire 32 ! PC [31:0] $end
$var wire 32 " INSTRUCTION [31:0] $end
$var reg 1 # CLK $end
$var reg 1 $ RESET $end
$scope module mycpu $end
$var wire 1 # CLK $end
$var wire 32 % INSTRUCTION [31:0] $end
$var wire 1 $ RESET $end
$var wire 1 & WRITE_ENABLE $end
$var wire 8 ' TWOS [7:0] $end
$var wire 1 ( SUB_SELECT $end
$var wire 8 ) SUB_RESULT [7:0] $end
$var wire 8 * REGOUT2 [7:0] $end
$var wire 8 + REGOUT1 [7:0] $end
$var wire 32 , NEXTPC [31:0] $end
$var wire 1 - IMM_SELECT $end
$var wire 8 . IMM_RESULT [7:0] $end
$var wire 8 / ALU_OUT [7:0] $end
$var wire 3 0 ALUOP [2:0] $end
$var reg 32 1 PC [31:0] $end
$scope module adr $end
$var wire 32 2 FOUR [31:0] $end
$var wire 32 3 PC [31:0] $end
$var wire 32 4 NEXTPC [31:0] $end
$upscope $end
$scope module alu $end
$var wire 3 5 SELECT [2:0] $end
$var wire 8 6 OR_OUT [7:0] $end
$var wire 8 7 FORWARD_OUT [7:0] $end
$var wire 8 8 DATA2 [7:0] $end
$var wire 8 9 DATA1 [7:0] $end
$var wire 8 : AND_OUT [7:0] $end
$var wire 8 ; ADD_OUT [7:0] $end
$var reg 8 < RESULT [7:0] $end
$scope module add1 $end
$var wire 8 = DATA2 [7:0] $end
$var wire 8 > DATA1 [7:0] $end
$var wire 8 ? ADD_OUT [7:0] $end
$upscope $end
$scope module and1 $end
$var wire 8 @ AND_OUT [7:0] $end
$var wire 8 A DATA2 [7:0] $end
$var wire 8 B DATA1 [7:0] $end
$upscope $end
$scope module fwd1 $end
$var wire 8 C FORWARD_OUT [7:0] $end
$var wire 8 D DATA2 [7:0] $end
$upscope $end
$scope module or1 $end
$var wire 8 E OR_OUT [7:0] $end
$var wire 8 F DATA2 [7:0] $end
$var wire 8 G DATA1 [7:0] $end
$upscope $end
$upscope $end
$scope module for_sub $end
$var wire 8 H OUTPUT [7:0] $end
$var wire 8 I INPUT [7:0] $end
$upscope $end
$scope module immediate_or_reg $end
$var wire 8 J INPUT2 [7:0] $end
$var wire 1 - SELECT $end
$var wire 8 K INPUT1 [7:0] $end
$var reg 8 L OUTPUT [7:0] $end
$upscope $end
$scope module mucu $end
$var wire 8 M OPCODE [7:0] $end
$var reg 3 N ALUOP [2:0] $end
$var reg 1 - MUXIMM $end
$var reg 1 ( MUXSUB $end
$var reg 1 & WRITEENABLE $end
$upscope $end
$scope module myregfile $end
$var wire 1 # CLK $end
$var wire 8 O IN [7:0] $end
$var wire 3 P INADDRESS [2:0] $end
$var wire 8 Q OUT1 [7:0] $end
$var wire 3 R OUT1ADDRESS [2:0] $end
$var wire 8 S OUT2 [7:0] $end
$var wire 3 T OUT2ADDRESS [2:0] $end
$var wire 1 $ RESET $end
$var wire 1 & WRITE $end
$upscope $end
$scope module select2s $end
$var wire 8 U INPUT1 [7:0] $end
$var wire 8 V INPUT2 [7:0] $end
$var wire 1 ( SELECT $end
$var reg 8 W OUTPUT [7:0] $end
$upscope $end
$upscope $end
$upscope $end
$enddefinitions $end
#0
$dumpvars
bx W
bx V
bx U
bx T
bx S
bx R
bx Q
bx P
bx O
bx N
bx M
bx L
bx K
bx J
bx I
bx H
bx G
bx F
bx E
bx D
bx C
bx B
bx A
bx @
bx ?
bx >
bx =
bx <
bx ;
bx :
bx 9
bx 8
bx 7
bx 6
bx 5
bx 4
b0 3
b100 2
b0 1
bx 0
bx /
bx .
x-
bx ,
bx +
bx *
bx )
x(
bx '
x&
bx %
1$
0#
bx "
b0 !
$end
#1
b100 ,
b100 4
#2
b101 .
b101 8
b101 =
b101 A
b101 D
b101 F
b101 L
b0 M
b100 P
b0 R
b101 T
b101 J
b1000000000000000101 "
b1000000000000000101 %
#3
b101 /
b101 <
b101 O
bx1x1 6
bx1x1 E
b0x0x :
b0x0x @
1&
0(
b0 0
b0 5
b0 N
1-
b101 7
b101 C
#4
1#
#5
0$
#7
b0 )
b0 K
b0 W
b0 *
b0 I
b0 S
b0 U
b0 +
b0 9
b0 >
b0 B
b0 G
b0 Q
#8
b0 '
b0 H
b0 V
b101 6
b101 E
b0 :
b0 @
0#
#9
b101 ;
b101 ?
#12
1#
#13
b100 !
b100 1
b100 3
#14
b1000 ,
b1000 4
#15
b1001 .
b1001 8
b1001 =
b1001 A
b1001 D
b1001 F
b1001 L
b10 P
b1 T
b1001 J
b100000000000001001 "
b100000000000001001 %
#16
b1001 /
b1001 <
b1001 O
b1001 6
b1001 E
b1001 7
b1001 C
0#
#17
b1001 ;
b1001 ?
#20
1#
#21
b1000 !
b1000 1
b1000 3
#22
b1100 ,
b1100 4
#23
b10 .
b10 8
b10 =
b10 A
b10 D
b10 F
b10 L
b10 M
b110 P
b100 R
b10 T
b10 J
b10000001100000010000000010 "
b10000001100000010000000010 %
#24
b0 .
b0 8
b0 =
b0 A
b0 D
b0 F
b0 L
b10 6
b10 E
b1 0
b1 5
b1 N
0-
b10 7
b10 C
0#
#25
b1001 .
b1001 8
b1001 =
b1001 A
b1001 D
b1001 F
b1001 L
b1001 )
b1001 K
b1001 W
b0 6
b0 E
b0 7
b0 C
b101 +
b101 9
b101 >
b101 B
b101 G
b101 Q
b1001 *
b1001 I
b1001 S
b1001 U
#26
b1 :
b1 @
b1001 7
b1001 C
b1101 6
b1101 E
b11110111 '
b11110111 H
b11110111 V
#27
b1110 /
b1110 <
b1110 O
b1110 ;
b1110 ?
#28
1#
#29
b1100 !
b1100 1
b1100 3
#30
b10000 ,
b10000 4
#31
b1 M
b0 P
b0 R
b110 T
b110 J
b1000000000000000000000110 "
b1000000000000000000000110 %
#32
0#
#33
b1110 .
b1110 8
b1110 =
b1110 A
b1110 D
b1110 F
b1110 L
b1110 )
b1110 K
b1110 W
b0 +
b0 9
b0 >
b0 B
b0 G
b0 Q
b1110 *
b1110 I
b1110 S
b1110 U
#34
b1110 7
b1110 C
b1110 6
b1110 E
b0 :
b0 @
b11110010 '
b11110010 H
b11110010 V
#36
1#
#37
b10000 !
b10000 1
b10000 3
#38
b10100 ,
b10100 4
#39
b0 M
b1 P
b1 T
b1 J
b1110 +
b1110 9
b1110 >
b1110 B
b1110 G
b1110 Q
b10000000000000001 "
b10000000000000001 %
#40
b1 .
b1 8
b1 =
b1 A
b1 D
b1 F
b1 L
b0 0
b0 5
b0 N
1-
b1110 :
b1110 @
0#
#41
b1 /
b1 <
b1 O
b0 )
b0 K
b0 W
b1111 6
b1111 E
b0 :
b0 @
b1 7
b1 C
b0 *
b0 I
b0 S
b0 U
#42
b0 '
b0 H
b0 V
b1111 ;
b1111 ?
#44
1#
#45
b10100 !
b10100 1
b10100 3
#46
b11000 ,
b11000 4
#47
b1 )
b1 K
b1 W
b10 M
b10 P
b10 R
b1 *
b1 I
b1 S
b1 U
b10000000100000001000000001 "
b10000000100000001000000001 %
#48
b1111 /
b1111 <
b1111 O
b1 0
b1 5
b1 N
0-
b11111111 '
b11111111 H
b11111111 V
0#
#49
b1001 +
b1001 9
b1001 >
b1001 B
b1001 G
b1001 Q
#50
b1001 6
b1001 E
b1 :
b1 @
#51
b1010 /
b1010 <
b1010 O
b1010 ;
b1010 ?
#52
1#
#53
b11000 !
b11000 1
b11000 3
#54
b11100 ,
b11100 4
#55
bx M
bx P
bx R
bx T
bx J
b1010 +
b1010 9
b1010 >
b1010 B
b1010 G
b1010 Q
bx "
bx %
#56
b1011 6
b1011 E
b0 :
b0 @
0#
#57
bx .
bx 8
bx =
bx A
bx D
bx F
bx L
bx )
bx K
bx W
b1011 /
b1011 <
b1011 O
bx +
bx 9
bx >
bx B
bx G
bx Q
bx *
bx I
bx S
bx U
b1011 ;
b1011 ?
#58
bx 7
bx C
bx 6
bx E
bx :
bx @
bx '
bx H
bx V
#59
bx /
bx <
bx O
bx ;
bx ?
#60
1#
#61
b11100 !
b11100 1
b11100 3
#62
b100000 ,
b100000 4
#64
0#
#68
1#
#69
b100000 !
b100000 1
b100000 3
#70
b100100 ,
b100100 4
#72
0#
#76
1#
#77
b100100 !
b100100 1
b100100 3
#78
b101000 ,
b101000 4
#80
0#
#84
1#
#85
b101000 !
b101000 1
b101000 3
#86
b101100 ,
b101100 4
#88
0#
#92
1#
#93
b101100 !
b101100 1
b101100 3
#94
b110000 ,
b110000 4
#96
0#
#100
1#
#101
b110000 !
b110000 1
b110000 3
#102
b110100 ,
b110100 4
#104
0#
#108
1#
#109
b110100 !
b110100 1
b110100 3
#110
b111000 ,
b111000 4
#112
0#
#116
1#
#117
b111000 !
b111000 1
b111000 3
#118
b111100 ,
b111100 4
#120
0#
#124
1#
#125
b111100 !
b111100 1
b111100 3
#126
b1000000 ,
b1000000 4
#128
0#
#132
1#
#133
b1000000 !
b1000000 1
b1000000 3
#134
b1000100 ,
b1000100 4
#136
0#
#140
1#
#141
b1000100 !
b1000100 1
b1000100 3
#142
b1001000 ,
b1001000 4
#144
0#
#148
1#
#149
b1001000 !
b1001000 1
b1001000 3
#150
b1001100 ,
b1001100 4
#152
0#
#156
1#
#157
b1001100 !
b1001100 1
b1001100 3
#158
b1010000 ,
b1010000 4
#160
0#
#164
1#
#165
b1010000 !
b1010000 1
b1010000 3
#166
b1010100 ,
b1010100 4
#168
0#
#172
1#
#173
b1010100 !
b1010100 1
b1010100 3
#174
b1011000 ,
b1011000 4
#176
0#
#180
1#
#181
b1011000 !
b1011000 1
b1011000 3
#182
b1011100 ,
b1011100 4
#184
0#
#188
1#
#189
b1011100 !
b1011100 1
b1011100 3
#190
b1100000 ,
b1100000 4
#192
0#
#196
1#
#197
b1100000 !
b1100000 1
b1100000 3
#198
b1100100 ,
b1100100 4
#200
0#
#204
1#
#205
b1100100 !
b1100100 1
b1100100 3
#206
b1101000 ,
b1101000 4
#208
0#
#212
1#
#213
b1101000 !
b1101000 1
b1101000 3
#214
b1101100 ,
b1101100 4
#216
0#
#220
1#
#221
b1101100 !
b1101100 1
b1101100 3
#222
b1110000 ,
b1110000 4
#224
0#
#228
1#
#229
b1110000 !
b1110000 1
b1110000 3
#230
b1110100 ,
b1110100 4
#232
0#
#236
1#
#237
b1110100 !
b1110100 1
b1110100 3
#238
b1111000 ,
b1111000 4
#240
0#
#244
1#
#245
b1111000 !
b1111000 1
b1111000 3
#246
b1111100 ,
b1111100 4
#248
0#
#252
1#
#253
b1111100 !
b1111100 1
b1111100 3
#254
b10000000 ,
b10000000 4
#256
0#
#260
1#
#261
b10000000 !
b10000000 1
b10000000 3
#262
b10000100 ,
b10000100 4
#264
0#
#268
1#
#269
b10000100 !
b10000100 1
b10000100 3
#270
b10001000 ,
b10001000 4
#272
0#
#276
1#
#277
b10001000 !
b10001000 1
b10001000 3
#278
b10001100 ,
b10001100 4
#280
0#
#284
1#
#285
b10001100 !
b10001100 1
b10001100 3
#286
b10010000 ,
b10010000 4
#288
0#
#292
1#
#293
b10010000 !
b10010000 1
b10010000 3
#294
b10010100 ,
b10010100 4
#296
0#
#300
1#
#301
b10010100 !
b10010100 1
b10010100 3
#302
b10011000 ,
b10011000 4
#304
0#
#308
1#
#309
b10011000 !
b10011000 1
b10011000 3
#310
b10011100 ,
b10011100 4
#312
0#
#316
1#
#317
b10011100 !
b10011100 1
b10011100 3
#318
b10100000 ,
b10100000 4
#320
0#
#324
1#
#325
b10100000 !
b10100000 1
b10100000 3
#326
b10100100 ,
b10100100 4
#328
0#
#332
1#
#333
b10100100 !
b10100100 1
b10100100 3
#334
b10101000 ,
b10101000 4
#336
0#
#340
1#
#341
b10101000 !
b10101000 1
b10101000 3
#342
b10101100 ,
b10101100 4
#344
0#
#348
1#
#349
b10101100 !
b10101100 1
b10101100 3
#350
b10110000 ,
b10110000 4
#352
0#
#356
1#
#357
b10110000 !
b10110000 1
b10110000 3
#358
b10110100 ,
b10110100 4
#360
0#
#364
1#
#365
b10110100 !
b10110100 1
b10110100 3
#366
b10111000 ,
b10111000 4
#368
0#
#372
1#
#373
b10111000 !
b10111000 1
b10111000 3
#374
b10111100 ,
b10111100 4
#376
0#
#380
1#
#381
b10111100 !
b10111100 1
b10111100 3
#382
b11000000 ,
b11000000 4
#384
0#
#388
1#
#389
b11000000 !
b11000000 1
b11000000 3
#390
b11000100 ,
b11000100 4
#392
0#
#396
1#
#397
b11000100 !
b11000100 1
b11000100 3
#398
b11001000 ,
b11001000 4
#400
0#
#404
1#
#405
b11001000 !
b11001000 1
b11001000 3
#406
b11001100 ,
b11001100 4
#408
0#
#412
1#
#413
b11001100 !
b11001100 1
b11001100 3
#414
b11010000 ,
b11010000 4
#416
0#
#420
1#
#421
b11010000 !
b11010000 1
b11010000 3
#422
b11010100 ,
b11010100 4
#424
0#
#428
1#
#429
b11010100 !
b11010100 1
b11010100 3
#430
b11011000 ,
b11011000 4
#432
0#
#436
1#
#437
b11011000 !
b11011000 1
b11011000 3
#438
b11011100 ,
b11011100 4
#440
0#
#444
1#
#445
b11011100 !
b11011100 1
b11011100 3
#446
b11100000 ,
b11100000 4
#448
0#
#452
1#
#453
b11100000 !
b11100000 1
b11100000 3
#454
b11100100 ,
b11100100 4
#456
0#
#460
1#
#461
b11100100 !
b11100100 1
b11100100 3
#462
b11101000 ,
b11101000 4
#464
0#
#468
1#
#469
b11101000 !
b11101000 1
b11101000 3
#470
b11101100 ,
b11101100 4
#472
0#
#476
1#
#477
b11101100 !
b11101100 1
b11101100 3
#478
b11110000 ,
b11110000 4
#480
0#
#484
1#
#485
b11110000 !
b11110000 1
b11110000 3
#486
b11110100 ,
b11110100 4
#488
0#
#492
1#
#493
b11110100 !
b11110100 1
b11110100 3
#494
b11111000 ,
b11111000 4
#496
0#
#500
1#
#501
b11111000 !
b11111000 1
b11111000 3
#502
b11111100 ,
b11111100 4
