lab5/reg.v
/*
 *
 *	Part 2 - Register File
 *  Group 2
 *
 */

module Eight_bit_reg(IN, OUT1, OUT2, INADDRESS, OUT1ADDRESS, OUT2ADDRESS, WRITE, CLK, RESET);

	input WRITE, CLK, RESET;				// 1-bit inputs
	input [2:0] INADDRESS, OUT1ADDRESS, OUT2ADDRESS;	// 3-bits inputs
	input [7:0] IN;						// 8-bits input

	output [7:0] OUT1, OUT2;				// 8-bits outputs


	reg [7:0] registers[7:0];		// this represents the 8-bits(1 byte)  8 registers ( 8x8 registers )


	integer regNum ;			// represet the register number for the RESET task

	// assign given addresses values to OUT1 and OUT2 respectively. this is asynchronous therefore, we use blocking statement with delay 2 units
	assign #2 OUT1 = registers[OUT1ADDRESS];	
	assign #2 OUT2 = registers[OUT2ADDRESS];


	// write to given address register at positive edge of the clock
	always @(posedge CLK) 
	begin 
		// writting happens when WRITE is high. 
		// if statement includes only one row so don't use begin end keywords
		if ( WRITE )	
			
			// this is synchronous therefore, we use non-blocking statement with delay 1 unit.
			// write in to given register
			#1 registers[INADDRESS] <= IN ;


	

	// reset all the registers synchronously at the positive edge of the clock
	
	
		
		// reset all the registers when RESET is high. 
		if ( RESET ) #1
		begin
			/*
			for(regNum = 0; regNum < 8 ; regNum = regNum + 1)begin
			
				registers[regNum] <= 'b00000000;

			end
			*/
			registers[0] <= 'b00000000;
			registers[1] <= 'b00000000;
			registers[2] <= 'b00000000;
			registers[3] <= 'b00000000;
			registers[4] <= 'b00000000;
			registers[5] <= 'b00000000;
			registers[6] <= 'b00000000;
			registers[7] <= 'b00000000;
			
		end
	
	end

endmodule

lab5/reg_file_tb.v
// Computer Architecture (CO224) - Lab 05
// Design: Register File Testbench of Simple Processor
// Author: Kisaru Liyanage
// Date	: 21-October-2020
`include "reg.v"
module reg_file_tb;
    
    reg [7:0] WRITEDATA;
    reg [2:0] WRITEREG, READREG1, READREG2;
    reg CLK, RESET, WRITEENABLE; 
    wire [7:0] REGOUT1, REGOUT2;
    
    Eight_bit_reg myregfile(WRITEDATA, REGOUT1, REGOUT2, WRITEREG, READREG1, READREG2, WRITEENABLE, CLK, RESET);
       
    initial
    begin
        CLK = 1'b1;
        
        // generate files needed to plot the waveform using GTKWave
        $dumpfile("reg_file_wavedata.vcd");
		$dumpvars(0, reg_file_tb);
        
        // assign values with time to input signals to see output 
        RESET = 1'b0;
        WRITEENABLE = 1'b0;
        
        #5
        RESET = 1'b1;
        READREG1 = 3'd0;
        READREG2 = 3'd4;
        
        #7
        RESET = 1'b0;
        
        #3
        WRITEREG = 3'd2;
        WRITEDATA = 8'd95;
        WRITEENABLE = 1'b1;
        
        #9
        WRITEENABLE = 1'b0;
        
        #1
        READREG1 = 3'd2;
        
        #9
        WRITEREG = 3'd1;
        WRITEDATA = 8'd28;
        WRITEENABLE = 1'b1;
        READREG1 = 3'd1;
        
        #10
        WRITEENABLE = 1'b0;
        
        #10
        WRITEREG = 3'd4;
        WRITEDATA = 8'd6;
        WRITEENABLE = 1'b1;
        
        #10
        WRITEDATA = 8'd15;
        WRITEENABLE = 1'b1;
        
        #10
        WRITEENABLE = 1'b0;
        
        #6
        WRITEREG = 3'd1;
        WRITEDATA = 8'd50;
        WRITEENABLE = 1'b1;
        
        #5
        WRITEENABLE = 1'b0;
        
        #10
        $finish;
    end
    
    // clock signal generation
    always
        #5 CLK = ~CLK;
        

endmodule

lab5/reg_file_wavedata.vcd
$date
	Sun Jan  9 10:18:30 2022
$end
$version
	Icarus Verilog
$end
$timescale
	1s
$end
$scope module reg_file_tb $end
$var wire 8 ! REGOUT2 [7:0] $end
$var wire 8 " REGOUT1 [7:0] $end
$var reg 1 # CLK $end
$var reg 3 $ READREG1 [2:0] $end
$var reg 3 % READREG2 [2:0] $end
$var reg 1 & RESET $end
$var reg 8 ' WRITEDATA [7:0] $end
$var reg 1 ( WRITEENABLE $end
$var reg 3 ) WRITEREG [2:0] $end
$scope module myregfile $end
$var wire 1 # CLK $end
$var wire 8 * IN [7:0] $end
$var wire 3 + INADDRESS [2:0] $end
$var wire 8 , OUT1 [7:0] $end
$var wire 3 - OUT1ADDRESS [2:0] $end
$var wire 8 . OUT2 [7:0] $end
$var wire 3 / OUT2ADDRESS [2:0] $end
$var wire 1 & RESET $end
$var wire 1 ( WRITE $end
$upscope $end
$upscope $end
$enddefinitions $end
#0
$dumpvars
bx /
bx .
bx -
bx ,
bx +
bx *
bx )
0(
bx '
0&
bx %
bx $
1#
bx "
bx !
$end
#5
0#
b100 %
b100 /
b0 $
b0 -
1&
#10
1#
#12
0&
#13
b0 !
b0 .
b0 "
b0 ,
#15
1(
b1011111 '
b1011111 *
b10 )
b10 +
0#
#20
1#
#24
0(
#25
b10 $
b10 -
0#
#27
b1011111 "
b1011111 ,
#30
1#
#34
b1 $
b1 -
1(
b11100 '
b11100 *
b1 )
b1 +
#35
0#
#36
b0 "
b0 ,
#40
1#
#43
b11100 "
b11100 ,
#44
0(
#45
0#
#50
1#
#54
1(
b110 '
b110 *
b100 )
b100 +
#55
0#
#60
1#
#63
b110 !
b110 .
#64
b1111 '
b1111 *
#65
0#
#70
1#
#73
b1111 !
b1111 .
#74
0(
#75
0#
#80
1#
1(
b110010 '
b110010 *
b1 )
b1 +
#83
b110010 "
b110010 ,
#85
0#
0(
