lab5/alu.v
module Alu (RESULT, DATA1, DATA2, SELECT);
input [7:0] DATA1, DATA2;
input [2:0] SELECT;
output reg [7:0] RESULT;
wire [7:0] ADD_OUT, FORWARD_OUT, AND_OUT, OR_OUT;

Forward fwd1(FORWARD_OUT, DATA2 );
Add add1(ADD_OUT, DATA1, DATA2 );
And and1(AND_OUT, DATA1, DATA2 );
Or or1(OR_OUT, DATA1, DATA2 );

always @(SELECT, DATA1, DATA2) begin //always @(*) begin
    

    case (SELECT)
        0:
            #1 RESULT = FORWARD_OUT;
        1:
            #2 RESULT = ADD_OUT; 
        2:
            #1 RESULT = AND_OUT; 
        3:
            #1 RESULT = OR_OUT; 
        default:
            RESULT = 0;

    endcase
end

endmodule

module Forward (FORWARD_OUT, DATA2);
    input [7:0]  DATA2;
    output [7:0] FORWARD_OUT;
    assign FORWARD_OUT =  DATA2; 
    
endmodule

module Add (ADD_OUT, DATA1, DATA2);
    input [7:0] DATA1, DATA2;
    output [7:0] ADD_OUT;
    assign ADD_OUT =  DATA1+DATA2; 
    
endmodule

module And (AND_OUT, DATA1, DATA2);
    input [7:0] DATA1, DATA2;
    output [7:0] AND_OUT;
    assign AND_OUT =  DATA1 & DATA2; 
    
endmodule

module Or (OR_OUT, DATA1, DATA2);
    input [7:0] DATA1, DATA2;
    output [7:0] OR_OUT;
    assign OR_OUT =  DATA1 | DATA2; 
    
endmodule

lab5/testalu.v
`include "alu.v"

module testbench ;
    reg [7:0] DATA1, DATA2 ;
    reg [2:0] SELECT;
    wire [7:0] RESULT;


Alu alu(RESULT, DATA1, DATA2, SELECT);
initial begin 
    $dumpfile("wavedata.vcd");
    $dumpvars(0, testbench);

    DATA1=  17;
    DATA2 = 15;


SELECT = 0;
#5       $display("DATA1= %d, DATA2= %d, SELECT= %d, RESULT =%d", DATA1, DATA2, SELECT, RESULT);

SELECT = 1;
#5      $display("DATA1= %d, DATA2= %d, SELECT= %d, RESULT =%d", DATA1, DATA2, SELECT, RESULT);

SELECT = 2;
#5      $display("DATA1= %d, DATA2= %d, SELECT= %d, RESULT =%d", DATA1, DATA2, SELECT, RESULT);

SELECT = 3;
#5      $display("DATA1= %d, DATA2= %d, SELECT= %d, RESULT =%d", DATA1, DATA2, SELECT, RESULT);


$finish;
end
   
endmodule

lab5/wavedata.vcd
$date
	Thu Jan  6 11:30:57 2022
$end
$version
	Icarus Verilog
$end
$timescale
	1s
$end
$scope module testbench $end
$var wire 8 ! RESULT [7:0] $end
$var reg 8 " DATA1 [7:0] $end
$var reg 8 # DATA2 [7:0] $end
$var reg 3 $ SELECT [2:0] $end
$scope module alu $end
$var wire 8 % DATA1 [7:0] $end
$var wire 8 & DATA2 [7:0] $end
$var wire 3 ' SELECT [2:0] $end
$var wire 8 ( OR_OUT [7:0] $end
$var wire 8 ) FORWARD_OUT [7:0] $end
$var wire 8 * AND_OUT [7:0] $end
$var wire 8 + ADD_OUT [7:0] $end
$var reg 8 , RESULT [7:0] $end
$scope module add1 $end
$var wire 8 - DATA1 [7:0] $end
$var wire 8 . DATA2 [7:0] $end
$var wire 8 / ADD_OUT [7:0] $end
$upscope $end
$scope module and1 $end
$var wire 8 0 AND_OUT [7:0] $end
$var wire 8 1 DATA1 [7:0] $end
$var wire 8 2 DATA2 [7:0] $end
$upscope $end
$scope module fwd1 $end
$var wire 8 3 DATA2 [7:0] $end
$var wire 8 4 FORWARD_OUT [7:0] $end
$upscope $end
$scope module or1 $end
$var wire 8 5 DATA1 [7:0] $end
$var wire 8 6 DATA2 [7:0] $end
$var wire 8 7 OR_OUT [7:0] $end
$upscope $end
$upscope $end
$upscope $end
$enddefinitions $end
#0
$dumpvars
b11111 7
b1111 6
b10001 5
b1111 4
b1111 3
b1111 2
b10001 1
b1 0
b100000 /
b1111 .
b10001 -
bx ,
b100000 +
b1 *
b1111 )
b11111 (
b0 '
b1111 &
b10001 %
b0 $
b1111 #
b10001 "
bx !
$end
#1
b1111 !
b1111 ,
#5
b1 $
b1 '
#7
b100000 !
b100000 ,
#10
b10 $
b10 '
#11
b1 !
b1 ,
#15
b11 $
b11 '
#16
b11111 !
b11111 ,
