lab5/part4/cpu.v
`include "reg.v"
`include "alu.v"

    // opcodes
    // loadi= "00000000";
	// mov 	= "00000001";
	// add 	= "00000010";
	// sub 	= "00000011";
	// and 	= "00000100";
	// or 	= "00000101";
    // j	= "00000110";
	// beq	= "00000111";

module cpu (PC, INSTRUCTION, CLK, RESET );
    input CLK, RESET;
    input [31:0] INSTRUCTION;
    output reg [31:0] PC ;
    

    wire SUB_SELECT, IMM_SELECT, WRITE_ENABLE, ZERO,BRANCH,JUMP, AND_OUT;
    wire [7:0] ALU_OUT, REGOUT1, REGOUT2, TWOS, SUB_RESULT, IMM_RESULT;
    wire [2:0] ALUOP;
    wire [31:0] NEXTPC,B_MUX_OUT, ADDR_OUT, NEXTPC2;
    
        //  opcode = INSTRUCTION[31:24]; // opcode
        //  rd = INSTRUCTION[23:16];     // destination
        //  rt = INSTRUCTION[15:8];      // operand 1
        //  rs = INSTRUCTION[7:0];       // operand 2 or immediate
    cu mucu(ALUOP, WRITE_ENABLE,SUB_SELECT, IMM_SELECT ,BRANCH,JUMP, INSTRUCTION[31:24] );
    reg_file myregfile(ALU_OUT, REGOUT1, REGOUT2, INSTRUCTION[18:16], INSTRUCTION[10:8],INSTRUCTION[2:0], WRITE_ENABLE, CLK, RESET);
    twos_comp for_sub(TWOS, REGOUT2);
    mux select2s(SUB_RESULT, REGOUT2, TWOS, SUB_SELECT);
    mux immediate_or_reg(IMM_RESULT, SUB_RESULT, INSTRUCTION[7:0], IMM_SELECT);
    Alu alu(ZERO, ALU_OUT, REGOUT1, IMM_RESULT, ALUOP);  
    addr adr(NEXTPC, PC, 'd4);

    andgate a1(AND_OUT, BRANCH, ZERO);
    newaddr na(ADDR_OUT, NEXTPC, INSTRUCTION[23:16]);
    mux32 branch_mux(B_MUX_OUT, NEXTPC, ADDR_OUT , AND_OUT );
    mux32 jump_mux (NEXTPC2  ,B_MUX_OUT, ADDR_OUT,JUMP);

    

    always @(posedge CLK) begin
        if(RESET) PC = 0;
        else #1 PC = NEXTPC2;
    end

endmodule


module mux (OUTPUT, INPUT1, INPUT2, SELECT);
    input SELECT;
    input[7:0] INPUT1, INPUT2;
    output reg [7:0] OUTPUT;
    always @(*) begin
        if (SELECT==0) OUTPUT = INPUT1;
        else OUTPUT = INPUT2;
    end
    
endmodule


module twos_comp (OUTPUT, INPUT);
    input[7:0] INPUT;
    output[7:0] OUTPUT;
    assign  #1 OUTPUT = ~INPUT+1;
    
    
endmodule

module   cu(ALUOP, WRITEENABLE, MUXSUB, MUXIMM,BRANCH,JUMP, OPCODE);
    input [7:0] OPCODE;
    output reg WRITEENABLE, MUXSUB, MUXIMM, BRANCH, JUMP;
    output reg [2:0] ALUOP;

    always @(*) begin
        #1
        case (OPCODE)   /// INSTRUCTION[31:24]
            
            'b00000000: begin // loadi
                MUXIMM = 'b1 ;// select for immediate value for loadi 
                ALUOP = 3'b000;
                MUXSUB = 'b0;
                WRITEENABLE = 'b1;
                BRANCH = 'b0;
                JUMP = 'b0;

            end 

            'b00000001: begin  // mov
                MUXIMM = 'b0;
                ALUOP = 3'b000;
                MUXSUB = 'b0;
                WRITEENABLE = 'b1;
                BRANCH = 'b0;
                JUMP = 'b0;
            end

            'b00000010: begin // add
                MUXIMM = 'b0 ;
                ALUOP = 3'b001;
                MUXSUB = 'b0;
                WRITEENABLE = 'b1;
                BRANCH = 'b0;
                JUMP = 'b0;
            end
                
            'b00000011: begin // sub
                MUXIMM = 'b0 ;
                ALUOP = 3'b001;
                MUXSUB = 'b1;
                WRITEENABLE = 'b1;
                BRANCH = 'b0;
                JUMP = 'b0;
            end

            'b00000100: begin // and
                MUXIMM = 'b0 ;
                ALUOP = 3'b010;
                MUXSUB = 'b0;
                WRITEENABLE = 'b1;
                BRANCH = 'b0;
                JUMP = 'b0;
            end

            'b00000101: begin // or
                MUXIMM = 'b0 ;
                ALUOP = 3'b011;
                MUXSUB = 'b0;
                WRITEENABLE = 'b1;
                BRANCH = 'b0;
                JUMP = 'b0;
            end
            
            'b00000110: begin // jump
                MUXIMM = 'bx ;
                ALUOP = 3'bxxx;
                MUXSUB = 'bx;
                WRITEENABLE = 'b0;
                BRANCH = 'b0;
                JUMP = 'b1;
            end

            'b00000111: begin // branch
                MUXIMM = 'bx ;
                ALUOP = 3'bxxx;
                MUXSUB = 'bx;
                WRITEENABLE = 'b0;
                BRANCH = 'b1;
                JUMP = 'b0;
            end

            default: begin
                MUXIMM = 'bx ;
                ALUOP = 3'bxxx;
                MUXSUB = 'bx;
                WRITEENABLE = 'b0;
                BRANCH = 'bx;
                JUMP = 'bx;
            end
                
        endcase   
    end
endmodule


module addr (NEXTPC, PC, FOUR);

input [31:0] PC, FOUR ;
output [31:0] NEXTPC;
assign  #1 NEXTPC =  PC + FOUR;


    
endmodule

module newaddr (NEW_ADDR, CURRENT_ADDR, OFFSET);

input[7:0] OFFSET;
input [31:0]  CURRENT_ADDR ;
output [31:0] NEW_ADDR;
wire[31:0] EXTENDED, SHIFTED;

assign EXTENDED = { {24{OFFSET[7]}}, OFFSET[7:0] };
assign SHIFTED = EXTENDED *4;
assign  #2 NEW_ADDR =  SHIFTED + CURRENT_ADDR ;


    
endmodule


module andgate (OUTPUT, INPUT1, INPUT2);
    input INPUT1, INPUT2;
    output OUTPUT;
    assign OUTPUT = INPUT1 & INPUT2;
endmodule

module mux32 (OUTPUT, INPUT1, INPUT2, SELECT);
    input SELECT;
    input[31:0] INPUT1, INPUT2;
    output reg [31:0] OUTPUT;
    always @(*) begin
        if (SELECT==0) OUTPUT = INPUT1;
        else if (SELECT ==1) OUTPUT = INPUT2;
    end
    
endmodule

lab5/part4/alu.v
module Alu (ZERO, RESULT, DATA1, DATA2, SELECT);

// port declaration
input [7:0] DATA1, DATA2;
input [2:0] SELECT;
output reg [7:0] RESULT;
output reg ZERO;

wire [7:0] ADD_OUT, FORWARD_OUT, AND_OUT, OR_OUT;


// module initializw
Forward fwd1(FORWARD_OUT, DATA2 );
Add add1(ADD_OUT, DATA1, DATA2 );
And and1(AND_OUT, DATA1, DATA2 );
Or or1(OR_OUT, DATA1, DATA2 );

always @(*) begin //always @(*) begin
    
    if ((DATA1-DATA2)==0) ZERO = 1;
    else ZERO = 0;
    
      
    case (SELECT)
        'b000:
             RESULT = FORWARD_OUT;
        'b001:
            RESULT = ADD_OUT; 
        'b010:
            RESULT = AND_OUT; 
        'b011:
            RESULT = OR_OUT; 
        default:
            RESULT = 'b00000000;

    endcase
end

  


endmodule

// arithmatic modules

module Forward (FORWARD_OUT, DATA2);
    input [7:0]  DATA2;
    output [7:0] FORWARD_OUT;
    assign #1 FORWARD_OUT =  DATA2; 
    
endmodule

module Add (ADD_OUT, DATA1, DATA2);
    input [7:0] DATA1, DATA2;
    output [7:0] ADD_OUT;
    assign #2  ADD_OUT =  DATA1+DATA2; 
    
endmodule

module And (AND_OUT, DATA1, DATA2);
    input [7:0] DATA1, DATA2;
    output [7:0] AND_OUT;
    assign #1 AND_OUT =  DATA1 & DATA2; 
    
endmodule

module Or (OR_OUT, DATA1, DATA2);
    input [7:0] DATA1, DATA2;
    output [7:0] OR_OUT;
    assign  #1 OR_OUT =  DATA1 | DATA2; 
    
endmodule

lab5/reg.v
/*
 *
 *	Part 2 - Register File
 *  Group 2
 *
 */

module reg_file(IN, OUT1, OUT2, INADDRESS, OUT1ADDRESS, OUT2ADDRESS, WRITE, CLK, RESET);

	input WRITE, CLK, RESET;				// 1-bit inputs
	input [2:0] INADDRESS, OUT1ADDRESS, OUT2ADDRESS;	// 3-bits inputs
	input [7:0] IN;						// 8-bits input

	output [7:0] OUT1, OUT2;				// 8-bits outputs


	reg [7:0] registers[7:0];		// this represents the 8-bits(1 byte)  8 registers ( 8x8 registers )


	integer regNum ;			// represet the register number for the RESET task

	// assign given addresses values to OUT1 and OUT2 respectively. this is asynchronous therefore, we use blocking statement with delay 2 units
	assign #2 OUT1 = registers[OUT1ADDRESS];	
	assign #2 OUT2 = registers[OUT2ADDRESS];


	// write to given address register at positive edge of the clock
	always @(posedge CLK) 
	begin 
		// writting happens when WRITE is high. 
		// if statement includes only one row so don't use begin end keywords
		if ( WRITE )	
			
			// this is synchronous therefore, we use non-blocking statement with delay 1 unit.
			// write in to given register
			#1 registers[INADDRESS] <= IN ;


	

	// reset all the registers synchronously at the positive edge of the clock
	
	
		
		// reset all the registers when RESET is high. 
		if ( RESET ) #1
		begin
			/*
			for(regNum = 0; regNum < 8 ; regNum = regNum + 1)begin
			
				registers[regNum] <= 'b00000000;

			end
			*/
			registers[0] <= 'b00000000;
			registers[1] <= 'b00000000;
			registers[2] <= 'b00000000;
			registers[3] <= 'b00000000;
			registers[4] <= 'b00000000;
			registers[5] <= 'b00000000;
			registers[6] <= 'b00000000;
			registers[7] <= 'b00000000;
			
		end
	
	end

endmodule

lab5/cpu_tb.v
// Computer Architecture (CO224) - Lab 05
// Design: Testbench of Integrated CPU of Simple Processor
// Author: Isuru Nawinne

`include "cpu.v"

module cpu_tb;

    reg CLK, RESET;
    wire [31:0] PC ;
    wire [31:0] INSTRUCTION;
    
    /* 
    ------------------------
     SIMPLE INSTRUCTION MEM
    ------------------------
    */
    
    // TODO: Initialize an array of registers (8x1024) named 'instr_mem' to be used as instruction memory
	
	reg [7:0] instr_mem [1023:0]; 	// instruction array
    
    // TODO: Create combinational logic to support CPU instruction fetching, given the Program Counter(PC) value 
    //       (make sure you include the delay for instruction fetching here)
    
	assign #2 INSTRUCTION = {instr_mem[PC+3],instr_mem[PC+2],instr_mem[PC+1],instr_mem[PC]};	// fetching instruction with time delay
	
    initial
    begin
        // Initialize instruction memory with the set of instructions you need execute on CPU
        
        // METHOD 1: manually loading instructions to instr_mem
        //{instr_mem[10'd3], instr_mem[10'd2], instr_mem[10'd1], instr_mem[10'd0]} = 32'b00000000000001000000000000000101;
        //{instr_mem[10'd7], instr_mem[10'd6], instr_mem[10'd5], instr_mem[10'd4]} = 32'b00000000000000100000000000001001;
        //{instr_mem[10'd11], instr_mem[10'd10], instr_mem[10'd9], instr_mem[10'd8]} = 32'b00000010000001100000010000000010;
		
        // METHOD 2: loading instr_mem content from instr_mem.mem file
        $readmemb("instr_mem.mem", instr_mem);
    end
    
    /* 
    -----
     CPU
    -----
    */
    cpu mycpu(PC, INSTRUCTION, CLK, RESET);

    initial
    begin
    
        // generate files needed to plot the waveform using GTKWave
        $dumpfile("cpu_wavedata.vcd");
		$dumpvars(0, cpu_tb);
        
        CLK = 1'b0;
        RESET = 1'b0;
        
        // TODO: Reset the CPU (by giving a pulse to RESET signal) to start the program execution
        RESET = 1'b1;
        #5
        RESET = 1'b0;

        // reset check
        //#20
        //RESET = 1'b1;
        //#5
        //RESET = 1'b0;
        //
		
		
        // finish simulation after some time
        #500
        $finish;
        
    end
    
    // clock signal generation
    always
        #4 CLK = ~CLK;
        

endmodule

lab5/part4/cpu_wavedata.vcd
$date
	Tue Feb  1 21:37:37 2022
$end
$version
	Icarus Verilog
$end
$timescale
	1s
$end
$scope module cpu_tb $end
$var wire 32 ! PC [31:0] $end
$var wire 32 " INSTRUCTION [31:0] $end
$var reg 1 # CLK $end
$var reg 1 $ RESET $end
$scope module mycpu $end
$var wire 1 # CLK $end
$var wire 32 % INSTRUCTION [31:0] $end
$var wire 1 $ RESET $end
$var wire 1 & ZERO $end
$var wire 1 ' WRITE_ENABLE $end
$var wire 8 ( TWOS [7:0] $end
$var wire 1 ) SUB_SELECT $end
$var wire 8 * SUB_RESULT [7:0] $end
$var wire 8 + REGOUT2 [7:0] $end
$var wire 8 , REGOUT1 [7:0] $end
$var wire 32 - NEXTPC2 [31:0] $end
$var wire 32 . NEXTPC [31:0] $end
$var wire 1 / JUMP $end
$var wire 1 0 IMM_SELECT $end
$var wire 8 1 IMM_RESULT [7:0] $end
$var wire 32 2 B_MUX_OUT [31:0] $end
$var wire 1 3 BRANCH $end
$var wire 1 4 AND_OUT $end
$var wire 8 5 ALU_OUT [7:0] $end
$var wire 3 6 ALUOP [2:0] $end
$var wire 32 7 ADDR_OUT [31:0] $end
$var reg 32 8 PC [31:0] $end
$scope module a1 $end
$var wire 1 4 OUTPUT $end
$var wire 1 & INPUT2 $end
$var wire 1 3 INPUT1 $end
$upscope $end
$scope module adr $end
$var wire 32 9 FOUR [31:0] $end
$var wire 32 : PC [31:0] $end
$var wire 32 ; NEXTPC [31:0] $end
$upscope $end
$scope module alu $end
$var wire 3 < SELECT [2:0] $end
$var wire 8 = OR_OUT [7:0] $end
$var wire 8 > FORWARD_OUT [7:0] $end
$var wire 8 ? DATA2 [7:0] $end
$var wire 8 @ DATA1 [7:0] $end
$var wire 8 A AND_OUT [7:0] $end
$var wire 8 B ADD_OUT [7:0] $end
$var reg 8 C RESULT [7:0] $end
$var reg 1 & ZERO $end
$scope module add1 $end
$var wire 8 D DATA2 [7:0] $end
$var wire 8 E DATA1 [7:0] $end
$var wire 8 F ADD_OUT [7:0] $end
$upscope $end
$scope module and1 $end
$var wire 8 G AND_OUT [7:0] $end
$var wire 8 H DATA2 [7:0] $end
$var wire 8 I DATA1 [7:0] $end
$upscope $end
$scope module fwd1 $end
$var wire 8 J FORWARD_OUT [7:0] $end
$var wire 8 K DATA2 [7:0] $end
$upscope $end
$scope module or1 $end
$var wire 8 L OR_OUT [7:0] $end
$var wire 8 M DATA2 [7:0] $end
$var wire 8 N DATA1 [7:0] $end
$upscope $end
$upscope $end
$scope module branch_mux $end
$var wire 32 O INPUT1 [31:0] $end
$var wire 1 4 SELECT $end
$var wire 32 P INPUT2 [31:0] $end
$var reg 32 Q OUTPUT [31:0] $end
$upscope $end
$scope module for_sub $end
$var wire 8 R OUTPUT [7:0] $end
$var wire 8 S INPUT [7:0] $end
$upscope $end
$scope module immediate_or_reg $end
$var wire 8 T INPUT2 [7:0] $end
$var wire 1 0 SELECT $end
$var wire 8 U INPUT1 [7:0] $end
$var reg 8 V OUTPUT [7:0] $end
$upscope $end
$scope module jump_mux $end
$var wire 32 W INPUT1 [31:0] $end
$var wire 1 / SELECT $end
$var wire 32 X INPUT2 [31:0] $end
$var reg 32 Y OUTPUT [31:0] $end
$upscope $end
$scope module mucu $end
$var wire 8 Z OPCODE [7:0] $end
$var reg 3 [ ALUOP [2:0] $end
$var reg 1 3 BRANCH $end
$var reg 1 / JUMP $end
$var reg 1 0 MUXIMM $end
$var reg 1 ) MUXSUB $end
$var reg 1 ' WRITEENABLE $end
$upscope $end
$scope module myregfile $end
$var wire 1 # CLK $end
$var wire 8 \ IN [7:0] $end
$var wire 3 ] INADDRESS [2:0] $end
$var wire 8 ^ OUT1 [7:0] $end
$var wire 3 _ OUT1ADDRESS [2:0] $end
$var wire 8 ` OUT2 [7:0] $end
$var wire 3 a OUT2ADDRESS [2:0] $end
$var wire 1 $ RESET $end
$var wire 1 ' WRITE $end
$upscope $end
$scope module na $end
$var wire 32 b CURRENT_ADDR [31:0] $end
$var wire 8 c OFFSET [7:0] $end
$var wire 32 d SHIFTED [31:0] $end
$var wire 32 e NEW_ADDR [31:0] $end
$var wire 32 f EXTENDED [31:0] $end
$upscope $end
$scope module select2s $end
$var wire 8 g INPUT1 [7:0] $end
$var wire 8 h INPUT2 [7:0] $end
$var wire 1 ) SELECT $end
$var reg 8 i OUTPUT [7:0] $end
$upscope $end
$upscope $end
$upscope $end
$enddefinitions $end
#0
$dumpvars
bx i
bx h
bx g
bx f
bx e
bx d
bx c
bx b
bx a
bx `
bx _
bx ^
bx ]
bx \
bx [
bx Z
bx Y
bx X
bx W
bx V
bx U
bx T
bx S
bx R
bx Q
bx P
bx O
bx N
bx M
bx L
bx K
bx J
bx I
bx H
bx G
bx F
bx E
bx D
bx C
bx B
bx A
bx @
bx ?
bx >
bx =
bx <
bx ;
bx :
b100 9
bx 8
bx 7
bx 6
bx 5
x4
x3
bx 2
bx 1
x0
x/
bx .
bx -
bx ,
bx +
bx *
x)
bx (
x'
x&
bx %
1$
0#
bx "
bx !
$end
#4
b0 !
b0 8
b0 :
1#
#5
b100 .
b100 ;
b100 O
b100 b
0$
#6
b10000 d
b0 Z
b100 ]
b0 _
b101 a
b101 T
b100 f
b100 c
b1000000000000000101 "
b1000000000000000101 %
#7
b100 -
b100 Y
b100 2
b100 Q
b100 W
04
0&
b101 1
b101 ?
b101 D
b101 H
b101 K
b101 M
b101 V
0/
03
1'
0)
b0 6
b0 <
b0 [
10
#8
b101 5
b101 C
b101 \
b0 *
b0 U
b0 i
bx1x1 =
bx1x1 L
b0x0x A
b0x0x G
b101 >
b101 J
b10100 7
b10100 P
b10100 X
b10100 e
b0 ,
b0 @
b0 E
b0 I
b0 N
b0 ^
b0 +
b0 S
b0 `
b0 g
0#
#9
b101 =
b101 L
b0 A
b0 G
b0 (
b0 R
b0 h
#10
b101 B
b101 F
#12
1#
#13
b100 !
b100 8
b100 :
#14
b1000 -
b1000 Y
b1000 2
b1000 Q
b1000 W
b1000 .
b1000 ;
b1000 O
b1000 b
#15
b101 ]
b10100 d
b101 f
b101 c
b1010000000000000101 "
b1010000000000000101 %
#16
0#
#17
b11100 7
b11100 P
b11100 X
b11100 e
#20
1#
#21
b1000 !
b1000 8
b1000 :
#22
b1100 -
b1100 Y
b1100 2
b1100 Q
b1100 W
b1100 .
b1100 ;
b1100 O
b1100 b
#23
b0 1
b0 ?
b0 D
b0 H
b0 K
b0 M
b0 V
b101 *
b101 U
b101 i
b110 Z
b10 ]
b0 a
b0 T
b1000 d
b10 f
b10 c
b101 +
b101 S
b101 `
b101 g
b110000000100000000000000000 "
b110000000100000000000000000 %
#24
b11100 -
b11100 Y
b0 5
b0 C
b0 \
b0 =
b0 L
1/
0'
x)
bx 6
bx <
bx [
x0
b0 >
b0 J
b11111011 (
b11111011 R
b11111011 h
0#
#25
1&
b10100 -
b10100 Y
b0 B
b0 F
b0 +
b0 S
b0 `
b0 g
b10100 7
b10100 P
b10100 X
b10100 e
#26
b0 (
b0 R
b0 h
#28
1#
#29
b10100 !
b10100 8
b10100 :
#30
b11000 2
b11000 Q
b11000 W
b11000 .
b11000 ;
b11000 O
b11000 b
#31
b1 Z
b0 ]
b110 a
b110 T
b0 d
b0 f
b0 c
b1000000000000000000000110 "
b1000000000000000000000110 %
#32
b11000 -
b11000 Y
b0 *
b0 U
b0 i
b0 1
b0 ?
b0 D
b0 H
b0 K
b0 M
b0 V
0/
1'
0)
b0 6
b0 <
b0 [
00
0#
#33
b11000 7
b11000 P
b11000 X
b11000 e
#36
1#
#37
b11000 !
b11000 8
b11000 :
#38
b11100 -
b11100 Y
b11100 2
b11100 Q
b11100 W
b11100 .
b11100 ;
b11100 O
b11100 b
#39
b111 Z
b110 ]
b100 _
b101 a
b101 T
b11111111111111111111111111111000 d
b11111111111111111111111111111110 f
b11111110 c
b111111111100000010000000101 "
b111111111100000010000000101 %
#40
b11000 -
b11000 Y
b11000 2
b11000 Q
b11000 W
14
13
0'
1)
0#
#41
b10100 -
b10100 Y
b10100 2
b10100 Q
b10100 W
b101 ,
b101 @
b101 E
b101 I
b101 N
b101 ^
b101 +
b101 S
b101 `
b101 g
b10100 7
b10100 P
b10100 X
b10100 e
#42
b11111011 1
b11111011 ?
b11111011 D
b11111011 H
b11111011 K
b11111011 M
b11111011 V
b11111011 *
b11111011 U
b11111011 i
b101 =
b101 L
b11111011 (
b11111011 R
b11111011 h
#43
b11111011 5
b11111011 C
b11111011 \
b11111111 =
b11111111 L
b1 A
b1 G
b11111011 >
b11111011 J
#44
1#
#45
b10100 !
b10100 8
b10100 :
#46
b11000 .
b11000 ;
b11000 O
b11000 b
#47
b1 Z
b0 ]
b0 _
b110 a
b110 T
b0 d
b0 f
b0 c
b1000000000000000000000110 "
b1000000000000000000000110 %
#48
b11000 -
b11000 Y
b11000 2
b11000 Q
b11000 W
b101 1
b101 ?
b101 D
b101 H
b101 K
b101 M
b101 V
04
b101 *
b101 U
b101 i
03
1'
0)
0#
#49
b0 1
b0 ?
b0 D
b0 H
b0 K
b0 M
b0 V
b101 5
b101 C
b101 \
b0 *
b0 U
b0 i
b101 =
b101 L
b101 A
b101 G
b101 >
b101 J
b0 ,
b0 @
b0 E
b0 I
b0 N
b0 ^
b0 +
b0 S
b0 `
b0 g
b11000 7
b11000 P
b11000 X
b11000 e
#50
b0 5
b0 C
b0 \
b0 =
b0 L
b0 >
b0 J
b0 A
b0 G
b0 (
b0 R
b0 h
#52
1#
#53
b11000 !
b11000 8
b11000 :
#54
b11100 -
b11100 Y
b11100 2
b11100 Q
b11100 W
b11100 .
b11100 ;
b11100 O
b11100 b
#55
b111 Z
b110 ]
b100 _
b101 a
b101 T
b11111111111111111111111111111000 d
b11111111111111111111111111111110 f
b11111110 c
b111111111100000010000000101 "
b111111111100000010000000101 %
#56
b11000 -
b11000 Y
b11000 2
b11000 Q
b11000 W
14
13
0'
1)
0#
#57
b10100 -
b10100 Y
b10100 2
b10100 Q
b10100 W
b101 ,
b101 @
b101 E
b101 I
b101 N
b101 ^
b101 +
b101 S
b101 `
b101 g
b10100 7
b10100 P
b10100 X
b10100 e
#58
b11111011 1
b11111011 ?
b11111011 D
b11111011 H
b11111011 K
b11111011 M
b11111011 V
b11111011 *
b11111011 U
b11111011 i
b101 =
b101 L
b11111011 (
b11111011 R
b11111011 h
#59
b11111011 5
b11111011 C
b11111011 \
b11111111 =
b11111111 L
b1 A
b1 G
b11111011 >
b11111011 J
#60
1#
#61
b10100 !
b10100 8
b10100 :
#62
b11000 .
b11000 ;
b11000 O
b11000 b
#63
b1 Z
b0 ]
b0 _
b110 a
b110 T
b0 d
b0 f
b0 c
b1000000000000000000000110 "
b1000000000000000000000110 %
#64
b11000 -
b11000 Y
b11000 2
b11000 Q
b11000 W
b101 1
b101 ?
b101 D
b101 H
b101 K
b101 M
b101 V
04
b101 *
b101 U
b101 i
03
1'
0)
0#
#65
b0 1
b0 ?
b0 D
b0 H
b0 K
b0 M
b0 V
b101 5
b101 C
b101 \
b0 *
b0 U
b0 i
b101 =
b101 L
b101 A
b101 G
b101 >
b101 J
b0 ,
b0 @
b0 E
b0 I
b0 N
b0 ^
b0 +
b0 S
b0 `
b0 g
b11000 7
b11000 P
b11000 X
b11000 e
#66
b0 5
b0 C
b0 \
b0 =
b0 L
b0 >
b0 J
b0 A
b0 G
b0 (
b0 R
b0 h
#68
1#
#69
b11000 !
b11000 8
b11000 :
#70
b11100 -
b11100 Y
b11100 2
b11100 Q
b11100 W
b11100 .
b11100 ;
b11100 O
b11100 b
#71
b111 Z
b110 ]
b100 _
b101 a
b101 T
b11111111111111111111111111111000 d
b11111111111111111111111111111110 f
b11111110 c
b111111111100000010000000101 "
b111111111100000010000000101 %
#72
b11000 -
b11000 Y
b11000 2
b11000 Q
b11000 W
14
13
0'
1)
0#
1$
#73
b10100 -
b10100 Y
b10100 2
b10100 Q
b10100 W
b101 ,
b101 @
b101 E
b101 I
b101 N
b101 ^
b101 +
b101 S
b101 `
b101 g
b10100 7
b10100 P
b10100 X
b10100 e
#74
b11111011 1
b11111011 ?
b11111011 D
b11111011 H
b11111011 K
b11111011 M
b11111011 V
b11111011 *
b11111011 U
b11111011 i
b101 =
b101 L
b11111011 (
b11111011 R
b11111011 h
0$
#75
b11111011 5
b11111011 C
b11111011 \
b11111111 =
b11111111 L
b1 A
b1 G
b11111011 >
b11111011 J
#76
1#
#77
b10100 !
b10100 8
b10100 :
#78
b11000 .
b11000 ;
b11000 O
b11000 b
#79
b1 Z
b0 ]
b0 _
b110 a
b110 T
b0 d
b0 f
b0 c
b1000000000000000000000110 "
b1000000000000000000000110 %
#80
b11000 -
b11000 Y
b11000 2
b11000 Q
b11000 W
b101 1
b101 ?
b101 D
b101 H
b101 K
b101 M
b101 V
04
b101 *
b101 U
b101 i
03
1'
0)
0#
#81
b0 1
b0 ?
b0 D
b0 H
b0 K
b0 M
b0 V
b101 5
b101 C
b101 \
b0 *
b0 U
b0 i
b101 =
b101 L
b101 A
b101 G
b101 >
b101 J
b0 ,
b0 @
b0 E
b0 I
b0 N
b0 ^
b0 +
b0 S
b0 `
b0 g
b11000 7
b11000 P
b11000 X
b11000 e
#82
b0 5
b0 C
b0 \
b0 =
b0 L
b0 >
b0 J
b0 A
b0 G
b0 (
b0 R
b0 h
#84
1#
#85
b11000 !
b11000 8
b11000 :
#86
b11100 -
b11100 Y
b11100 2
b11100 Q
b11100 W
b11100 .
b11100 ;
b11100 O
b11100 b
#87
b111 Z
b110 ]
b100 _
b101 a
b101 T
b11111111111111111111111111111000 d
b11111111111111111111111111111110 f
b11111110 c
b111111111100000010000000101 "
b111111111100000010000000101 %
#88
b11000 -
b11000 Y
b11000 2
b11000 Q
b11000 W
14
13
0'
1)
0#
#89
b10100 -
b10100 Y
b10100 2
b10100 Q
b10100 W
b101 ,
b101 @
b101 E
b101 I
b101 N
b101 ^
b101 +
b101 S
b101 `
b101 g
b10100 7
b10100 P
b10100 X
b10100 e
#90
b11111011 1
b11111011 ?
b11111011 D
b11111011 H
b11111011 K
b11111011 M
b11111011 V
b11111011 *
b11111011 U
b11111011 i
b101 =
b101 L
b11111011 (
b11111011 R
b11111011 h
#91
b11111011 5
b11111011 C
b11111011 \
b11111111 =
b11111111 L
b1 A
b1 G
b11111011 >
b11111011 J
#92
1#
#93
b10100 !
b10100 8
b10100 :
#94
b11000 .
b11000 ;
b11000 O
b11000 b
#95
b1 Z
b0 ]
b0 _
b110 a
b110 T
b0 d
b0 f
b0 c
b1000000000000000000000110 "
b1000000000000000000000110 %
#96
b11000 -
b11000 Y
b11000 2
b11000 Q
b11000 W
b101 1
b101 ?
b101 D
b101 H
b101 K
b101 M
b101 V
04
b101 *
b101 U
b101 i
03
1'
0)
0#
#97
b0 1
b0 ?
b0 D
b0 H
b0 K
b0 M
b0 V
b101 5
b101 C
b101 \
b0 *
b0 U
b0 i
b101 =
b101 L
b101 A
b101 G
b101 >
b101 J
b0 ,
b0 @
b0 E
b0 I
b0 N
b0 ^
b0 +
b0 S
b0 `
b0 g
b11000 7
b11000 P
b11000 X
b11000 e
#98
b0 5
b0 C
b0 \
b0 =
b0 L
b0 >
b0 J
b0 A
b0 G
b0 (
b0 R
b0 h
#100
1#
#101
b11000 !
b11000 8
b11000 :
#102
b11100 -
b11100 Y
b11100 2
b11100 Q
b11100 W
b11100 .
b11100 ;
b11100 O
b11100 b
#103
b111 Z
b110 ]
b100 _
b101 a
b101 T
b11111111111111111111111111111000 d
b11111111111111111111111111111110 f
b11111110 c
b111111111100000010000000101 "
b111111111100000010000000101 %
#104
b11000 -
b11000 Y
b11000 2
b11000 Q
b11000 W
14
13
0'
1)
0#
#105
b10100 -
b10100 Y
b10100 2
b10100 Q
b10100 W
b101 ,
b101 @
b101 E
b101 I
b101 N
b101 ^
b101 +
b101 S
b101 `
b101 g
b10100 7
b10100 P
b10100 X
b10100 e
#106
b11111011 1
b11111011 ?
b11111011 D
b11111011 H
b11111011 K
b11111011 M
b11111011 V
b11111011 *
b11111011 U
b11111011 i
b101 =
b101 L
b11111011 (
b11111011 R
b11111011 h
#107
b11111011 5
b11111011 C
b11111011 \
b11111111 =
b11111111 L
b1 A
b1 G
b11111011 >
b11111011 J
#108
1#
#109
b10100 !
b10100 8
b10100 :
#110
b11000 .
b11000 ;
b11000 O
b11000 b
#111
b1 Z
b0 ]
b0 _
b110 a
b110 T
b0 d
b0 f
b0 c
b1000000000000000000000110 "
b1000000000000000000000110 %
#112
b11000 -
b11000 Y
b11000 2
b11000 Q
b11000 W
b101 1
b101 ?
b101 D
b101 H
b101 K
b101 M
b101 V
04
b101 *
b101 U
b101 i
03
1'
0)
0#
#113
b0 1
b0 ?
b0 D
b0 H
b0 K
b0 M
b0 V
b101 5
b101 C
b101 \
b0 *
b0 U
b0 i
b101 =
b101 L
b101 A
b101 G
b101 >
b101 J
b0 ,
b0 @
b0 E
b0 I
b0 N
b0 ^
b0 +
b0 S
b0 `
b0 g
b11000 7
b11000 P
b11000 X
b11000 e
#114
b0 5
b0 C
b0 \
b0 =
b0 L
b0 >
b0 J
b0 A
b0 G
b0 (
b0 R
b0 h
#116
1#
#117
b11000 !
b11000 8
b11000 :
#118
b11100 -
b11100 Y
b11100 2
b11100 Q
b11100 W
b11100 .
b11100 ;
b11100 O
b11100 b
#119
b111 Z
b110 ]
b100 _
b101 a
b101 T
b11111111111111111111111111111000 d
b11111111111111111111111111111110 f
b11111110 c
b111111111100000010000000101 "
b111111111100000010000000101 %
#120
b11000 -
b11000 Y
b11000 2
b11000 Q
b11000 W
14
13
0'
1)
0#
#121
b10100 -
b10100 Y
b10100 2
b10100 Q
b10100 W
b101 ,
b101 @
b101 E
b101 I
b101 N
b101 ^
b101 +
b101 S
b101 `
b101 g
b10100 7
b10100 P
b10100 X
b10100 e
#122
b11111011 1
b11111011 ?
b11111011 D
b11111011 H
b11111011 K
b11111011 M
b11111011 V
b11111011 *
b11111011 U
b11111011 i
b101 =
b101 L
b11111011 (
b11111011 R
b11111011 h
#123
b11111011 5
b11111011 C
b11111011 \
b11111111 =
b11111111 L
b1 A
b1 G
b11111011 >
b11111011 J
#124
1#
#125
b10100 !
b10100 8
b10100 :
#126
b11000 .
b11000 ;
b11000 O
b11000 b
#127
b1 Z
b0 ]
b0 _
b110 a
b110 T
b0 d
b0 f
b0 c
b1000000000000000000000110 "
b1000000000000000000000110 %
#128
b11000 -
b11000 Y
b11000 2
b11000 Q
b11000 W
b101 1
b101 ?
b101 D
b101 H
b101 K
b101 M
b101 V
04
b101 *
b101 U
b101 i
03
1'
0)
0#
